{
  "registry_version": "1.0.0",
  "plugins": {
    "org-linter": {
      "current_version": "1.2.0",
      "versions": {
        "1.0.0": {
          "description": "Initial release of Porter organization linter",
          "features": ["Basic linting rules", "Shell script execution"],
          "git_ref": "v1.0.0"
        },
        "1.1.0": {
          "description": "Added configuration support and improved error messages",
          "features": ["Config file support", "Better error reporting", "Exit codes"],
          "git_ref": "v1.1.0"
        },
        "1.2.0": {
          "description": "Added support for multiple file types and custom rules",
          "features": ["Multi-file support", "Custom rule definitions", "JSON output"],
          "git_ref": "v1.2.0"
        }
      }
    },
    "db-seeder": {
      "current_version": "2.1.0",
      "versions": {
        "1.0.0": {
          "description": "Initial database seeder with basic functionality",
          "features": ["Basic seeding", "MySQL support"],
          "git_ref": "v1.0.0"
        },
        "2.0.0": {
          "description": "Major update with multi-database support",
          "features": ["PostgreSQL support", "Environment-specific configs", "Rollback functionality"],
          "git_ref": "v2.0.0"
        },
        "2.1.0": {
          "description": "Added MongoDB support and performance improvements",
          "features": ["MongoDB support", "Parallel seeding", "Progress indicators"],
          "git_ref": "v2.1.0"
        }
      }
    }
  }
}
